[
  {
    "name": "003_S_6260",
    "examdate": "2019-07-09"
  },
  {
    "name": "003_S_6644",
    "examdate": "2018-12-04"
  },
  {
    "name": "003_S_6833",
    "examdate": "2019-11-07"
  },
  {
    "name": "006_S_6243",
    "examdate": "2018-03-01"
  },
  {
    "name": "006_S_6277",
    "examdate": "2018-03-28"
  },
  {
    "name": "006_S_6375",
    "examdate": "2024-10-05"
  },
  {
    "name": "006_S_6441",
    "examdate": "2018-07-12"
  },
  {
    "name": "006_S_6770",
    "examdate": "2019-07-26"
  },
  {
    "name": "007_S_10258",
    "examdate": "2024-12-11"
  },
  {
    "name": "007_S_4488",
    "examdate": "2024-09-10"
  },
  {
    "name": "011_S_6465",
    "examdate": "2019-07-30"
  },
  {
    "name": "012_S_6760",
    "examdate": "2020-10-05"
  },
  {
    "name": "014_S_10157",
    "examdate": "2024-07-17"
  },
  {
    "name": "014_S_10236",
    "examdate": "2024-09-16"
  },
  {
    "name": "014_S_6145",
    "examdate": "2017-12-18"
  },
  {
    "name": "014_S_6145",
    "examdate": "2023-11-29"
  },
  {
    "name": "019_S_6573",
    "examdate": "2018-09-11"
  },
  {
    "name": "020_S_6185",
    "examdate": "2019-01-16"
  },
  {
    "name": "022_S_10306",
    "examdate": "2025-01-17"
  },
  {
    "name": "023_S_6356",
    "examdate": "2019-06-13"
  },
  {
    "name": "024_S_2239",
    "examdate": "2025-08-18"
  },
  {
    "name": "024_S_6202",
    "examdate": "2022-03-09"
  },
  {
    "name": "024_S_6202",
    "examdate": "2025-04-03"
  },
  {
    "name": "027_S_10618",
    "examdate": "2025-03-24"
  },
  {
    "name": "027_S_10728",
    "examdate": "2025-05-05"
  },
  {
    "name": "027_S_6849",
    "examdate": "2020-02-10"
  },
  {
    "name": "031_S_4721",
    "examdate": "2018-12-14"
  },
  {
    "name": "033_S_10099",
    "examdate": "2024-04-24"
  },
  {
    "name": "033_S_10249",
    "examdate": "2024-09-20"
  },
  {
    "name": "033_S_10793",
    "examdate": "2025-05-19"
  },
  {
    "name": "033_S_6705",
    "examdate": "2019-03-26"
  },
  {
    "name": "033_S_6889",
    "examdate": "2020-09-29"
  },
  {
    "name": "033_S_6889",
    "examdate": "2024-10-23"
  },
  {
    "name": "035_S_10241",
    "examdate": "2024-09-11"
  },
  {
    "name": "035_S_10274",
    "examdate": "2024-10-14"
  },
  {
    "name": "035_S_6488",
    "examdate": "2020-07-23"
  },
  {
    "name": "035_S_6488",
    "examdate": "2024-07-05"
  },
  {
    "name": "035_S_6730",
    "examdate": "2019-06-18"
  },
  {
    "name": "035_S_6948",
    "examdate": "2021-05-21"
  },
  {
    "name": "036_S_10133",
    "examdate": "2024-06-12"
  },
  {
    "name": "036_S_10595",
    "examdate": "2025-03-17"
  },
  {
    "name": "036_S_6466",
    "examdate": "2018-07-05"
  },
  {
    "name": "036_S_6897",
    "examdate": "2021-02-11"
  },
  {
    "name": "037_S_0377",
    "examdate": "2019-06-05"
  },
  {
    "name": "041_S_6159",
    "examdate": "2018-01-03"
  },
  {
    "name": "057_S_6869",
    "examdate": "2022-03-03"
  },
  {
    "name": "067_S_6957",
    "examdate": "2021-07-16"
  },
  {
    "name": "068_S_4431",
    "examdate": "2017-09-25"
  },
  {
    "name": "070_S_4856",
    "examdate": "2018-04-10"
  },
  {
    "name": "082_S_6197",
    "examdate": "2018-05-02"
  },
  {
    "name": "082_S_6563",
    "examdate": "2020-01-16"
  },
  {
    "name": "082_S_6629",
    "examdate": "2020-02-05"
  },
  {
    "name": "094_S_6250",
    "examdate": "2018-03-29"
  },
  {
    "name": "094_S_6269",
    "examdate": "2018-03-27"
  },
  {
    "name": "098_S_6534",
    "examdate": "2019-12-10"
  },
  {
    "name": "098_S_6534",
    "examdate": "2024-07-08"
  },
  {
    "name": "099_S_6025",
    "examdate": "2024-12-05"
  },
  {
    "name": "114_S_6113",
    "examdate": "2024-11-05"
  },
  {
    "name": "114_S_6429",
    "examdate": "2018-08-30"
  },
  {
    "name": "114_S_6429",
    "examdate": "2025-02-11"
  },
  {
    "name": "116_S_6428",
    "examdate": "2019-06-26"
  },
  {
    "name": "116_S_6750",
    "examdate": "2019-06-18"
  },
  {
    "name": "116_S_6750",
    "examdate": "2025-03-11"
  },
  {
    "name": "123_S_10648",
    "examdate": "2025-04-03"
  },
  {
    "name": "123_S_10726",
    "examdate": "2025-05-06"
  },
  {
    "name": "127_S_6024",
    "examdate": "2019-12-04"
  },
  {
    "name": "127_S_6203",
    "examdate": "2022-09-21"
  },
  {
    "name": "127_S_6203",
    "examdate": "2025-05-08"
  },
  {
    "name": "127_S_6330",
    "examdate": "2020-09-24"
  },
  {
    "name": "127_S_6549",
    "examdate": "2019-10-18"
  },
  {
    "name": "128_S_4607",
    "examdate": "2025-07-07"
  },
  {
    "name": "129_S_6459",
    "examdate": "2022-07-20"
  },
  {
    "name": "129_S_6784",
    "examdate": "2021-08-18"
  },
  {
    "name": "130_S_10337",
    "examdate": "2024-11-07"
  },
  {
    "name": "130_S_2403",
    "examdate": "2017-07-06"
  },
  {
    "name": "130_S_6329",
    "examdate": "2025-05-29"
  },
  {
    "name": "130_S_6688",
    "examdate": "2019-02-12"
  },
  {
    "name": "137_S_6693",
    "examdate": "2024-10-09"
  },
  {
    "name": "137_S_6919",
    "examdate": "2024-02-09"
  },
  {
    "name": "141_S_6015",
    "examdate": "2017-05-11"
  },
  {
    "name": "141_S_6253",
    "examdate": "2018-03-18"
  },
  {
    "name": "301_S_10139",
    "examdate": "2024-06-12"
  },
  {
    "name": "305_S_6810",
    "examdate": "2021-12-06"
  },
  {
    "name": "941_S_6384",
    "examdate": "2018-05-30"
  },
  {
    "name": "941_S_6514",
    "examdate": "2018-07-24"
  },
  {
    "name": "941_S_6575",
    "examdate": "2019-09-16"
  },
  {
    "name": "941_S_6581",
    "examdate": "2018-09-12"
  },
  {
    "name": "941_S_6854",
    "examdate": "2022-02-22"
  }
]